<annotation verified="yes">
    <folder>Annotation</folder>
    <filename>IMG20230605162416at216x216.jpg</filename>
    <path>object_detection-PascalVOC-export/Annotations/IMG20230605162416at216x216.jpg</path>
    <source>
        <database>Unknown</database>
    </source>
    <size>
        <width>216</width>
        <height>216</height>
        <depth>3</depth>
    </size>
    <segmented>0</segmented>
    <object>
    <name>insulator</name>
    <pose>Unspecified</pose>
    <truncated>0</truncated>
    <difficult>0</difficult>
    <bndbox>
        <xmin>19.100436681222707</xmin>
        <ymin>102.3406113537118</ymin>
        <xmax>133.23144104803492</xmax>
        <ymax>186.0524017467249</ymax>
    </bndbox>
</object>
</annotation>
