<annotation verified="yes">
    <folder>Annotation</folder>
    <filename>IMG20230605163024_01.jpg</filename>
    <path>insulator_detection-PascalVOC-export/Annotations/IMG20230605163024_01.jpg</path>
    <source>
        <database>Unknown</database>
    </source>
    <size>
        <width>216</width>
        <height>216</height>
        <depth>3</depth>
    </size>
    <segmented>0</segmented>
    <object>
    <name>insulator</name>
    <pose>Unspecified</pose>
    <truncated>0</truncated>
    <difficult>0</difficult>
    <bndbox>
        <xmin>72.51091703056768</xmin>
        <ymin>52.82096069868996</ymin>
        <xmax>192.77292576419214</xmax>
        <ymax>112.95196506550218</ymax>
    </bndbox>
</object>
</annotation>
