<annotation verified="yes">
    <folder>Annotation</folder>
    <filename>IMG20230605162337.jpg</filename>
    <path>insulator_detection-PascalVOC-export/Annotations/IMG20230605162337.jpg</path>
    <source>
        <database>Unknown</database>
    </source>
    <size>
        <width>216</width>
        <height>216</height>
        <depth>3</depth>
    </size>
    <segmented>0</segmented>
    <object>
    <name>insulator</name>
    <pose>Unspecified</pose>
    <truncated>0</truncated>
    <difficult>0</difficult>
    <bndbox>
        <xmin>55.29694323144105</xmin>
        <ymin>49.519650655021834</ymin>
        <xmax>176.97379912663757</xmax>
        <ymax>153.03930131004367</ymax>
    </bndbox>
</object>
</annotation>
